video_transformers/__init__.py
video_transformers/data.py
video_transformers/heads.py
video_transformers/modeling.py
video_transformers/necks.py
video_transformers/predict.py
video_transformers/schedulers.py
video_transformers/templates.py
video_transformers/tracking.py
video_transformers/trainer.py
video_transformers/auto/__init__.py
video_transformers/auto/backbone.py
video_transformers/auto/head.py
video_transformers/auto/neck.py
video_transformers/backbones/__init__.py
video_transformers/backbones/base.py
video_transformers/backbones/timm.py
video_transformers/backbones/transformers.py
video_transformers/deployment/__init__.py
video_transformers/deployment/gradio.py
video_transformers/deployment/onnx.py
video_transformers/hfhub_wrapper/__init__.py
video_transformers/hfhub_wrapper/hub_mixin.py
video_transformers/pytorchvideo_wrapper/__init__.py
video_transformers/pytorchvideo_wrapper/data/__init__.py
video_transformers/pytorchvideo_wrapper/data/labeled_video_dataset.py
video_transformers/pytorchvideo_wrapper/data/labeled_video_paths.py
video_transformers/tasks/__init__.py
video_transformers/tasks/base.py
video_transformers/tasks/single_label_classification.py
video_transformers/utils/__init__.py
video_transformers/utils/extra.py
video_transformers/utils/file.py
video_transformers/utils/imports.py
video_transformers/utils/logger.py
video_transformers/utils/torch.py
video_transformers-0.0.9.dist-info/LICENSE
video_transformers-0.0.9.dist-info/METADATA
video_transformers-0.0.9.dist-info/WHEEL
video_transformers-0.0.9.dist-info/top_level.txt
video_transformers-0.0.9.dist-info/RECORD
