Metadata-Version: 2.1
Name: video-transformers
Version: 0.0.9
Summary: Easiest way of fine-tuning HuggingFace video classification models.
Home-page: https://github.com/fcakyon/video-transformers
Author: fcakyon
License: MIT
Keywords: machine-learning,deep-learning,ml,pytorch,vision,loss,video-classification,transformers,accelerate,evaluate,huggingface
Classifier: Development Status :: 5 - Production/Stable
Classifier: Operating System :: OS Independent
Classifier: Intended Audience :: Developers
Classifier: Intended Audience :: Science/Research
Classifier: Programming Language :: Python :: 3
Classifier: Programming Language :: Python :: 3.7
Classifier: Programming Language :: Python :: 3.8
Classifier: Programming Language :: Python :: 3.9
Classifier: Topic :: Software Development :: Libraries
Classifier: Topic :: Software Development :: Libraries :: Python Modules
Classifier: Topic :: Education
Classifier: Topic :: Scientific/Engineering
Classifier: Topic :: Scientific/Engineering :: Artificial Intelligence
Requires-Python: >=3.7
License-File: LICENSE
Requires-Dist: accelerate (<0.15.0,>=0.14.0)
Requires-Dist: evaluate (<0.4.0,>=0.3.0)
Requires-Dist: transformers (>=4.25.0)
Requires-Dist: timm (<0.7.0,>=0.6.12)
Requires-Dist: click (==8.0.4)
Requires-Dist: balanced-loss
Requires-Dist: scikit-learn
Requires-Dist: tensorboard
Requires-Dist: opencv-python
Requires-Dist: gradio (>=3.1.6)
Requires-Dist: huggingface-hub (<0.12.0,>=0.11.0)
Requires-Dist: importlib-metadata (<4.3,>=1.1.0) ; python_version < "3.8"
Provides-Extra: dev
Requires-Dist: black (==21.7b0) ; extra == 'dev'
Requires-Dist: flake8 (==3.9.2) ; extra == 'dev'
Requires-Dist: isort (==5.9.2) ; extra == 'dev'
Provides-Extra: test
Requires-Dist: black (==21.7b0) ; extra == 'test'
Requires-Dist: flake8 (==3.9.2) ; extra == 'test'
Requires-Dist: isort (==5.9.2) ; extra == 'test'
Requires-Dist: onnx ; extra == 'test'
Requires-Dist: onnxruntime ; extra == 'test'
